MANIFEST.in
README.txt
bootstrap.py
buildout.cfg
setup.cfg
setup.py
docs/.DS_Store
docs/._.DS_Store
docs/Makefile
docs/conf.py
docs/conf.py~
docs/history.rst
docs/index.rst
docs/index.rst~
docs/make.bat
docs/options.rst
docs/options.rst~
docs/readme.rst
docs/sample.rst
docs/sample.rst~
docs/_build/.DS_Store
docs/_build/._.DS_Store
docs/_build/doctrees/environment.pickle
docs/_build/doctrees/history.doctree
docs/_build/doctrees/index.doctree
docs/_build/doctrees/options.doctree
docs/_build/doctrees/readme.doctree
docs/_build/doctrees/sample.doctree
docs/_build/html/.buildinfo
docs/_build/html/genindex.html
docs/_build/html/history.html
docs/_build/html/index.html
docs/_build/html/objects.inv
docs/_build/html/options.html
docs/_build/html/readme.html
docs/_build/html/sample.html
docs/_build/html/search.html
docs/_build/html/searchindex.js
docs/_build/html/_sources/history.txt
docs/_build/html/_sources/index.txt
docs/_build/html/_sources/options.txt
docs/_build/html/_sources/readme.txt
docs/_build/html/_sources/sample.txt
docs/_build/html/_static/background_b01.png
docs/_build/html/_static/background_r12.png
docs/_build/html/_static/basic.css
docs/_build/html/_static/doctools.js
docs/_build/html/_static/file.png
docs/_build/html/_static/jquery.js
docs/_build/html/_static/minus.png
docs/_build/html/_static/plus.png
docs/_build/html/_static/pygments.css
docs/_build/html/_static/searchtools.js
docs/_build/html/_static/trstyle.css
docs/_build/html/_static/trstyle.css_t~
docs/_build/html/_static/underscore.js
src/AUTHORS.txt
src/HISTORY.txt
src/LICENSE.txt
src/README.txt
src/sphinxjp/__init__.py
src/sphinxjp.themes.trstyle.egg-info/PKG-INFO
src/sphinxjp.themes.trstyle.egg-info/SOURCES.txt
src/sphinxjp.themes.trstyle.egg-info/dependency_links.txt
src/sphinxjp.themes.trstyle.egg-info/entry_points.txt
src/sphinxjp.themes.trstyle.egg-info/namespace_packages.txt
src/sphinxjp.themes.trstyle.egg-info/not-zip-safe
src/sphinxjp.themes.trstyle.egg-info/requires.txt
src/sphinxjp.themes.trstyle.egg-info/top_level.txt
src/sphinxjp/themes/__init__.py
src/sphinxjp/themes/trstyle/__init__.py
src/sphinxjp/themes/trstyle/templates/trstyle/layout.html
src/sphinxjp/themes/trstyle/templates/trstyle/theme.conf
src/sphinxjp/themes/trstyle/templates/trstyle/static/background_b01.png
src/sphinxjp/themes/trstyle/templates/trstyle/static/background_r12.png
