Metadata-Version: 1.0
Name: sphinxjp.themes.trstyle
Version: 0.1.0
Summary: A sphinx theme for TriAx Corp style Documentation.
Home-page: https://bitbucket.org/kironono/sphinxjp.themes.trstyle
Author: TriAx Corp
Author-email: junichi dot kakisako at triax dot jp
License: MIT
Keywords: sphinx,reStructuredText,theme
Platform: UNKNOWN
Classifier: Development Status :: 4 - Beta
Classifier: License :: OSI Approved :: MIT License
Classifier: Programming Language :: Python
Classifier: Topic :: Software Development
Classifier: Topic :: Software Development :: Documentation
Classifier: Topic :: Text Processing :: Markup
